buildup/__init__.py
buildup/core.py
buildup/__main__.py
buildup-0.1.data/data/templates/post.html
buildup-0.1.data/data/templates/index.html
buildup-0.1.data/data/templates/base.html
buildup-0.1.data/data/templates/page.html
buildup-0.1.dist-info/WHEEL
buildup-0.1.dist-info/RECORD
buildup-0.1.dist-info/METADATA
buildup-0.1.dist-info/metadata.json
buildup-0.1.dist-info/top_level.txt
buildup-0.1.dist-info/DESCRIPTION.rst
