Metadata-Version: 2.0
Name: buildup
Version: 0.1
Summary: Static Blog Generator
Home-page: UNKNOWN
Author: Chris Choi
Author-email: chutsu@gmail.com
License: UNKNOWN
Platform: UNKNOWN
Requires-Dist: markdown
Requires-Dist: jinja2
Requires-Dist: beautifulsoup4
